Metadata-Version: 1.0
Name: optimizelyAPI
Version: 0.6
Summary: Optimizely REST and Event API client package
Home-page: UNKNOWN
Author: Peter Katsos
Author-email: UNKNOWN
License: UNKNOWN
Platform: UNKNOWN
